Metadata-Version: 1.1
Name: rippcord
Version: 0.0.1
Summary: Useful methods for time series analysis
Home-page: UNKNOWN
Author: Gary Ewing
Author-email: workburner4321@gmail.com
License: MIT
Keywords: time series analysis
Platform: UNKNOWN
Classifier: Development Status :: 5 - Production/Stable
Classifier: Intended Audience :: Education
Classifier: Operating System :: Microsoft :: Windows :: Windows 10
Classifier: License :: OSI Approved :: MIT License
Classifier: Programming Language :: Python :: 3
